Chertoganov/Chertoganov.py
Chertoganov/__init__.py
Chertoganov/cli.py
Chertoganov-0.1.0.dist-info/AUTHORS.rst
Chertoganov-0.1.0.dist-info/LICENSE
Chertoganov-0.1.0.dist-info/METADATA
Chertoganov-0.1.0.dist-info/WHEEL
Chertoganov-0.1.0.dist-info/entry_points.txt
Chertoganov-0.1.0.dist-info/top_level.txt
Chertoganov-0.1.0.dist-info/RECORD
