Metadata-Version: 2.1
Name: Chertoganov
Version: 0.1.0
Summary: This is cool Package which is made by Chertoganov
Home-page: https://github.com/Chertoganov/Chertoganov
Author: Chertoganov
Author-email: chertoganov.kirill@gmail.com
License: MIT license
Keywords: Chertoganov
Platform: UNKNOWN
Classifier: Development Status :: 2 - Pre-Alpha
Classifier: Intended Audience :: Developers
Classifier: License :: OSI Approved :: MIT License
Classifier: Natural Language :: English
Classifier: Programming Language :: Python :: 3
Classifier: Programming Language :: Python :: 3.5
Classifier: Programming Language :: Python :: 3.6
Classifier: Programming Language :: Python :: 3.7
Classifier: Programming Language :: Python :: 3.8
Requires-Python: >=3.5
